[
  {
    "segment_id": "P04_21_ActiveUsage_0001",
    "start_time": 1.31,
    "end_time": 7.05,
    "start_frame": 78,
    "end_frame": 423,
    "objects_in_sequence": [
      {
        "class_id": 23,
        "class_name": "box",
        "name": "tupperware",
        "crop_frame_id": 353,
        "crop_bbox": [
          811.75,
          761.86,
          326.17,
          318.14
        ],
        "crop_image_name": "frame_0000000353.jpg"
      },
      {
        "class_id": 3,
        "class_name": "cupboard",
        "name": "cupboard",
        "crop_frame_id": 93,
        "crop_bbox": [
          1145.57,
          876.99,
          572.91,
          203.01
        ],
        "crop_image_name": "frame_0000000093.jpg"
      },
      {
        "class_id": 34,
        "class_name": "food",
        "name": "food",
        "crop_frame_id": 93,
        "crop_bbox": [
          929.25,
          231.66,
          260.96,
          195.87
        ],
        "crop_image_name": "frame_0000000093.jpg"
      },
      {
        "class_id": 20,
        "class_name": "spatula",
        "name": "sieve spatula",
        "crop_frame_id": 93,
        "crop_bbox": [
          1046.75,
          303.71,
          138.78,
          179.85
        ],
        "crop_image_name": "frame_0000000093.jpg"
      },
      {
        "class_id": 20,
        "class_name": "spatula",
        "name": "spatula",
        "crop_frame_id": 93,
        "crop_bbox": [
          1162.35,
          333.72,
          48.01,
          112.02
        ],
        "crop_image_name": "frame_0000000093.jpg"
      }
    ],
    "frame_ids": [
      93,
      119,
      187,
      234,
      353,
      407
    ],
    "narrations": [
      "open cupboard;1.31;2.32",
      "pick up tupperware;2.91;4.41",
      "put down tupperware;5.55;7.05"
    ]
  },
  {
    "segment_id": "P04_21_ActiveUsage_0002",
    "start_time": 7.61,
    "end_time": 94.24000000000001,
    "start_frame": 456,
    "end_frame": 5654,
    "objects_in_sequence": [
      {
        "class_id": 23,
        "class_name": "box",
        "name": "tupperware",
        "crop_frame_id": 860,
        "crop_bbox": [
          670.39,
          253.13,
          352.28,
          599.51
        ],
        "crop_image_name": "frame_0000000860.jpg"
      },
      {
        "class_id": 34,
        "class_name": "food",
        "name": "food",
        "crop_frame_id": 860,
        "crop_bbox": [
          1879.77,
          654.7,
          40.23,
          261.66
        ],
        "crop_image_name": "frame_0000000860.jpg"
      },
      {
        "class_id": 34,
        "class_name": "food",
        "name": "leftover food",
        "crop_frame_id": 4869,
        "crop_bbox": [
          213.49,
          778.72,
          128.67,
          126.12
        ],
        "crop_image_name": "frame_0000004869.jpg"
      },
      {
        "class_id": 14,
        "class_name": "fork",
        "name": "fork",
        "crop_frame_id": 860,
        "crop_bbox": [
          1221.19,
          571.86,
          159.74,
          289.98
        ],
        "crop_image_name": "frame_0000000860.jpg"
      },
      {
        "class_id": 12,
        "class_name": "fridge",
        "name": "fridge",
        "crop_frame_id": 4869,
        "crop_bbox": [
          542.15,
          0,
          1294.97,
          1043.14
        ],
        "crop_image_name": "frame_0000004869.jpg"
      },
      {
        "class_id": 24,
        "class_name": "hob",
        "name": "hob",
        "crop_frame_id": 860,
        "crop_bbox": [
          1145.33,
          338.98,
          774.67,
          740.97
        ],
        "crop_image_name": "frame_0000000860.jpg"
      },
      {
        "class_id": 20,
        "class_name": "spatula",
        "name": "sieve spatula",
        "crop_frame_id": 860,
        "crop_bbox": [
          761.68,
          527.78,
          138.81,
          264.39
        ],
        "crop_image_name": "frame_0000000860.jpg"
      },
      {
        "class_id": 20,
        "class_name": "spatula",
        "name": "spatula",
        "crop_frame_id": 860,
        "crop_bbox": [
          911.64,
          493.15,
          299.46,
          548.17
        ],
        "crop_image_name": "frame_0000000860.jpg"
      },
      {
        "class_id": 1,
        "class_name": "spoon",
        "name": "spoon",
        "crop_frame_id": 860,
        "crop_bbox": [
          1199.18,
          606.96,
          96.05,
          209.7
        ],
        "crop_image_name": "frame_0000000860.jpg"
      }
    ],
    "frame_ids": [
      860,
      2307,
      4869,
      5112,
      5543,
      5617
    ],
    "narrations": [
      "put leftover food in tupperware;7.61;50.86",
      "put tupperware in fridge;79.55;86.26",
      "pick up cutlery;91.94;94.24000000000001"
    ]
  },
  {
    "segment_id": "P04_21_ActiveUsage_0003",
    "start_time": 102.78,
    "end_time": 112.87,
    "start_frame": 6166,
    "end_frame": 6772,
    "objects_in_sequence": [
      {
        "class_id": 36,
        "class_name": "bin",
        "name": "food bin",
        "crop_frame_id": 6185,
        "crop_bbox": [
          1420.65,
          0,
          499.35,
          242.99
        ],
        "crop_image_name": "frame_0000006185.jpg"
      },
      {
        "class_id": 70,
        "class_name": "dishwasher",
        "name": "dishwasher",
        "crop_frame_id": 6241,
        "crop_bbox": [
          49.86,
          658.38,
          915.61,
          421.62
        ],
        "crop_image_name": "frame_0000006241.jpg"
      },
      {
        "class_id": 34,
        "class_name": "food",
        "name": "leftover food",
        "crop_frame_id": 6185,
        "crop_bbox": [
          1265.06,
          132.54,
          482.65,
          431.24
        ],
        "crop_image_name": "frame_0000006185.jpg"
      },
      {
        "class_id": 24,
        "class_name": "hob",
        "name": "hob",
        "crop_frame_id": 6767,
        "crop_bbox": [
          1371.24,
          6.28,
          548.76,
          600.96
        ],
        "crop_image_name": "frame_0000006767.jpg"
      },
      {
        "class_id": 20,
        "class_name": "spatula",
        "name": "sieve spatula",
        "crop_frame_id": 6185,
        "crop_bbox": [
          1207.93,
          134.23,
          169.32,
          422.03
        ],
        "crop_image_name": "frame_0000006185.jpg"
      }
    ],
    "frame_ids": [
      6185,
      6241,
      6449,
      6579,
      6715,
      6767
    ],
    "narrations": [
      "pick up spoon;102.78;104.16",
      "spread leftover food in food bin;105.85;111.41",
      "put spoon in dishwasher;111.50999999999999;112.87"
    ]
  },
  {
    "segment_id": "P04_21_ActiveUsage_0004",
    "start_time": 113.43,
    "end_time": 123.85,
    "start_frame": 6805,
    "end_frame": 7431,
    "objects_in_sequence": [
      {
        "class_id": 70,
        "class_name": "dishwasher",
        "name": "dishwasher",
        "crop_frame_id": 6953,
        "crop_bbox": [
          576.74,
          167.59,
          649.34,
          795.21
        ],
        "crop_image_name": "frame_0000006953.jpg"
      },
      {
        "class_id": 34,
        "class_name": "food",
        "name": "leftover food",
        "crop_frame_id": 6833,
        "crop_bbox": [
          851.56,
          201.1,
          743.38,
          558.81
        ],
        "crop_image_name": "frame_0000006833.jpg"
      },
      {
        "class_id": 24,
        "class_name": "hob",
        "name": "hob",
        "crop_frame_id": 6833,
        "crop_bbox": [
          768.8,
          250.81,
          852.24,
          554.03
        ],
        "crop_image_name": "frame_0000006833.jpg"
      },
      {
        "class_id": 5,
        "class_name": "pan",
        "name": "pan",
        "crop_frame_id": 6833,
        "crop_bbox": [
          1222.55,
          197.55,
          376.68,
          486.91
        ],
        "crop_image_name": "frame_0000006833.jpg"
      },
      {
        "class_id": 93,
        "class_name": "towel:kitchen",
        "name": "kitchen paper",
        "crop_frame_id": 7413,
        "crop_bbox": [
          635.17,
          615.18,
          333.78,
          420.71
        ],
        "crop_image_name": "frame_0000007413.jpg"
      },
      {
        "class_id": 93,
        "class_name": "towel:kitchen",
        "name": "kitchen roll",
        "crop_frame_id": 7357,
        "crop_bbox": [
          1059.05,
          32.94,
          324.75,
          651.67
        ],
        "crop_image_name": "frame_0000007357.jpg"
      }
    ],
    "frame_ids": [
      6833,
      6953,
      7028,
      7193,
      7357,
      7413
    ],
    "narrations": [
      "pick up pan;113.43;114.44",
      "put down pan;115.50999999999999;117.83",
      "get kitchen roll;122.05;123.85"
    ]
  },
  {
    "segment_id": "P04_21_ActiveUsage_0005",
    "start_time": 124.41,
    "end_time": 161.93,
    "start_frame": 7464,
    "end_frame": 9715,
    "objects_in_sequence": [
      {
        "class_id": 36,
        "class_name": "bin",
        "name": "bin/garbage can/recycling bin",
        "crop_frame_id": 8938,
        "crop_bbox": [
          710.9,
          482.58,
          512.2,
          597.42
        ],
        "crop_image_name": "frame_0000008938.jpg"
      },
      {
        "class_id": 34,
        "class_name": "food",
        "name": "leftover food",
        "crop_frame_id": 7870,
        "crop_bbox": [
          72.06,
          283.26,
          1196.62,
          654.43
        ],
        "crop_image_name": "frame_0000007870.jpg"
      },
      {
        "class_id": 24,
        "class_name": "hob",
        "name": "hob",
        "crop_frame_id": 7870,
        "crop_bbox": [
          66.94,
          13.44,
          1503.43,
          1066.56
        ],
        "crop_image_name": "frame_0000007870.jpg"
      },
      {
        "class_id": 5,
        "class_name": "pan",
        "name": "pan",
        "crop_frame_id": 8370,
        "crop_bbox": [
          75.54,
          -0.69,
          695.12,
          1031.43
        ],
        "crop_image_name": "frame_0000008370.jpg"
      },
      {
        "class_id": 2,
        "class_name": "plate",
        "name": "plate",
        "crop_frame_id": 9516,
        "crop_bbox": [
          1014.55,
          243.54,
          553.89,
          386.27
        ],
        "crop_image_name": "frame_0000009516.jpg"
      },
      {
        "class_id": 93,
        "class_name": "towel:kitchen",
        "name": "kitchen paper",
        "crop_frame_id": 7870,
        "crop_bbox": [
          1159.16,
          131.66,
          138.68,
          233.65
        ],
        "crop_image_name": "frame_0000007870.jpg"
      }
    ],
    "frame_ids": [
      7870,
      8370,
      8838,
      8938,
      9516,
      9656
    ],
    "narrations": [
      "clean up;124.41;146.32",
      "put kitchen roll in bin;146.72;150.14",
      "put leftover food in bin;157.87;161.93"
    ]
  },
  {
    "segment_id": "P04_21_ActiveUsage_0006",
    "start_time": 168.89,
    "end_time": 194.53,
    "start_frame": 10133,
    "end_frame": 11671,
    "objects_in_sequence": [
      {
        "class_id": 3,
        "class_name": "cupboard",
        "name": "cupboard",
        "crop_frame_id": 10614,
        "crop_bbox": [
          986.68,
          261.25,
          933.32,
          818.75
        ],
        "crop_image_name": "frame_0000010614.jpg"
      },
      {
        "class_id": 70,
        "class_name": "dishwasher",
        "name": "dishwasher",
        "crop_frame_id": 10288,
        "crop_bbox": [
          -1.52,
          0,
          1193.17,
          1080
        ],
        "crop_image_name": "frame_0000010288.jpg"
      },
      {
        "class_id": 2,
        "class_name": "plate",
        "name": "plate",
        "crop_frame_id": 10288,
        "crop_bbox": [
          471.81,
          425.56,
          289.64,
          397.63
        ],
        "crop_image_name": "frame_0000010288.jpg"
      },
      {
        "class_id": 171,
        "class_name": "tablet",
        "name": "tablet",
        "crop_frame_id": 11215,
        "crop_bbox": [
          845.37,
          688.58,
          28.81,
          29.17
        ],
        "crop_image_name": "frame_0000011215.jpg"
      }
    ],
    "frame_ids": [
      10288,
      10614,
      11049,
      11215,
      11443,
      11594
    ],
    "narrations": [
      "close dishwasher;168.89;180.08",
      "put tablet in dishwasher;181.9;188.9",
      "turn dishwasher on;188.96;194.53"
    ]
  }
]